black_tabby_formatter.py
black_tabby_formatter-0.1.1.dist-info/LICENSE
black_tabby_formatter-0.1.1.dist-info/METADATA
black_tabby_formatter-0.1.1.dist-info/WHEEL
black_tabby_formatter-0.1.1.dist-info/entry_points.txt
black_tabby_formatter-0.1.1.dist-info/top_level.txt
black_tabby_formatter-0.1.1.dist-info/RECORD
